biblib/__init__.py
biblib/main.py
biblibrary/__init__.py
biblibrary/main.py
biblibrary-1.0.1.dist-info/LICENSE.md
biblibrary-1.0.1.dist-info/METADATA
biblibrary-1.0.1.dist-info/WHEEL
biblibrary-1.0.1.dist-info/entry_points.txt
biblibrary-1.0.1.dist-info/top_level.txt
biblibrary-1.0.1.dist-info/RECORD
