Metadata-Version: 2.1
Name: biblibrary
Version: 1.0.1
Summary: A simple command line tool for bibliography management
Home-page: https://github.com/jagoosw/biblibrary
Author: Jago Strong-Wright
Author-email: jagoosw@protonmail.com
License: MIT
Download-URL: https://github.com/jagoosw/biblibrary/archive/1.0.0.tar.gz
Platform: UNKNOWN
Classifier: License :: OSI Approved :: MIT License
Classifier: Programming Language :: Python :: 3
Classifier: Programming Language :: Python :: 3.7
Requires-Python: >=3
Requires-Dist: Click (>=7.0)
Requires-Dist: pybtex (>=0.24.0)
Requires-Dist: thefuzz (>=0.19.0)
